LICENSE.txt
MANIFEST.in
README.md
pyproject.toml
setup.py
cf_plot.egg-info/PKG-INFO
cf_plot.egg-info/SOURCES.txt
cf_plot.egg-info/dependency_links.txt
cf_plot.egg-info/requires.txt
cf_plot.egg-info/top_level.txt
cfplot/__init__.py
cfplot/cfplot.py
cfplot/cfplot.py-allissuesfixedyay
cfplot/cfplot.py-fixesslb14
cfplot/cfplot.py-maskedwhitedoubles
cfplot/cfplot_a001.png
cfplot/cfplot_a002.png
cfplot/cfplot_a003.png
cfplot/era5_mon_sur_post1979.land.ant.timmean.nc
cfplot/era_test_script.py-sadie
cfplot/latest-traj-one.diff
cfplot/colourmaps/3gauss.rgb
cfplot/colourmaps/3saw.rgb
cfplot/colourmaps/BkBlAqGrYeOrReViWh200.rgb
cfplot/colourmaps/BlAqGrYeOrRe.rgb
cfplot/colourmaps/BlAqGrYeOrReVi200.rgb
cfplot/colourmaps/BlGrYeOrReVi200.rgb
cfplot/colourmaps/BlRe.rgb
cfplot/colourmaps/BlWhRe.rgb
cfplot/colourmaps/BlueDarkOrange18.rgb
cfplot/colourmaps/BlueDarkRed18.rgb
cfplot/colourmaps/BlueGreen14.rgb
cfplot/colourmaps/BlueRed.rgb
cfplot/colourmaps/BlueRedGray.rgb
cfplot/colourmaps/BlueWhiteOrangeRed.rgb
cfplot/colourmaps/BlueYellowRed.rgb
cfplot/colourmaps/BrBG.rgb
cfplot/colourmaps/BrownBlue12.rgb
cfplot/colourmaps/Cat12.rgb
cfplot/colourmaps/GHRSST_anomaly.rgb
cfplot/colourmaps/GrayWhiteGray.rgb
cfplot/colourmaps/GreenMagenta16.rgb
cfplot/colourmaps/GreenYellow.rgb
cfplot/colourmaps/OceanLakeLandSnow.rgb
cfplot/colourmaps/StepSeq25.rgb
cfplot/colourmaps/ViBlGrWhYeOrRe.rgb
cfplot/colourmaps/WhBlGrYeRe.rgb
cfplot/colourmaps/WhBlReWh.rgb
cfplot/colourmaps/WhViBlGrYeOrRe.rgb
cfplot/colourmaps/WhViBlGrYeOrReWh.rgb
cfplot/colourmaps/WhiteBlue.rgb
cfplot/colourmaps/WhiteBlueGreenYellowRed.rgb
cfplot/colourmaps/WhiteGreen.rgb
cfplot/colourmaps/WhiteYellowOrangeRed.rgb
cfplot/colourmaps/__init__.py
cfplot/colourmaps/amwg.rgb
cfplot/colourmaps/amwg256.rgb
cfplot/colourmaps/amwg_blueyellowred.rgb
cfplot/colourmaps/arctic.rgb
cfplot/colourmaps/cmp_b2r.rgb
cfplot/colourmaps/cmp_flux.rgb
cfplot/colourmaps/cmp_haxby.rgb
cfplot/colourmaps/colombia.rgb
cfplot/colourmaps/colournames.txt
cfplot/colourmaps/cosam.rgb
cfplot/colourmaps/cosam12.rgb
cfplot/colourmaps/default.rgb
cfplot/colourmaps/detail.rgb
cfplot/colourmaps/extrema.rgb
