Metadata-Version: 2.1
Name: cf-plot
Version: 3.4.0
Summary: Climate contour, vector and line plots in Python
Home-page: http://ajheaps.github.io/cf-plot
Author: Andy Heaps and Sadie Bartholomew
Author-email: andy.heaps@ncas.ac.uk
Maintainer: Sadie Bartholomew
Maintainer-email: sadie.bartholomew@ncas.ac.uk
License: LICENSE.txt
License-File: LICENSE.txt
Requires-Dist: cf-python>=3.17.0
Requires-Dist: cartopy>=0.22.0
